bili_listener-1.1.8.dist-info/METADATA
bili_listener-1.1.8.dist-info/WHEEL
bili_listener-1.1.8.dist-info/entry_points.txt
bili_listener-1.1.8.dist-info/licenses/LICENSE
blivedm/__init__.py
blivedm/clients/__init__.py
blivedm/clients/open_live.py
blivedm/clients/web.py
blivedm/clients/ws_base.py
blivedm/handlers.py
blivedm/models/__init__.py
blivedm/models/open_live.py
blivedm/models/web.py
blivedm/test/example/open_live_sample.py
blivedm/test/example/sample.py
blivedm/utils.py
bili_listener-1.1.8.dist-info/RECORD
