Metadata-Version: 2.1
Name: bili-listener
Version: 1.1.8
Summary: Python获取bilibili直播弹幕的库, 使用WebSocket协议
Keywords: bilibili,bilibili-live,danmaku
Author-Email: xfgryujk <xfgryujk@126.com>, Shadow403 <admin@shadow403.cn>
License: MIT License
Classifier: Development Status :: 5 - Production/Stable
Classifier: Framework :: AsyncIO
Classifier: Intended Audience :: Developers
Classifier: License :: OSI Approved :: MIT License
Classifier: Operating System :: OS Independent
Classifier: Programming Language :: Python :: 3
Classifier: Programming Language :: Python :: 3 :: Only
Classifier: Programming Language :: Python :: 3.8
Classifier: Programming Language :: Python :: 3.9
Classifier: Programming Language :: Python :: 3.10
Classifier: Programming Language :: Python :: 3.11
Classifier: Programming Language :: Python :: 3.12
Classifier: Programming Language :: Python :: 3.13
Classifier: Topic :: Internet :: WWW/HTTP
Classifier: Topic :: Software Development :: Libraries
Project-URL: Homepage, https://github.com/Shadow403/blivedm
Project-URL: Repository, https://github.com/Shadow403/blivedm
Project-URL: Issues, https://github.com/Shadow403/blivedm/issues
Requires-Python: >=3.8
Requires-Dist: aiohttp~=3.9.0
Requires-Dist: Brotli~=1.1.0
Requires-Dist: yarl~=1.18.3
Requires-Dist: loguru>=0.7.3
